angrt/__init__.py
angrt/narrator/common/v1/common_model.py
angrt/narrator/common/v1/common_p2p.py
angrt/narrator/common/v1/common_pb2.py
angrt/narrator/common/v1/common_pb2.pyi
angrt/narrator/common/v1/common_pb2_grpc.py
angrt/narrator/common/v1/common_pb2_grpc.pyi
angrt/narrator/templates/v1/template_service_model.py
angrt/narrator/templates/v1/template_service_p2p.py
angrt/narrator/templates/v1/template_service_pb2.py
angrt/narrator/templates/v1/template_service_pb2.pyi
angrt/narrator/templates/v1/template_service_pb2_grpc.py
angrt/narrator/templates/v1/template_service_pb2_grpc.pyi
angrt_narrator_contracts-0.1.2.dist-info/METADATA
angrt_narrator_contracts-0.1.2.dist-info/WHEEL
angrt_narrator_contracts-0.1.2.dist-info/entry_points.txt
angrt_narrator_contracts-0.1.2.dist-info/RECORD
